{
  "modelVersion" : "2.0",
  "id" : "listaImobileCumparator",
  "name" : "listaImobileCumparator",
  "lastUpdate" : 1619099826004,
  "rows" : [
    [
      {
        "type" : "container",
        "dimension" : {
          "xs" : 12,
          "sm" : 12,
          "md" : 12,
          "lg" : 12
        },
        "propertyValues" : {
          "cssClasses" : {
            "type" : "constant",
            "value" : ""
          },
          "hidden" : {
            "type" : "constant",
            "value" : false
          },
          "repeatedCollection" : {
            "type" : "variable",
            "value" : ""
          }
        },
        "reference" : "665ddc38-cf73-4579-8fe4-6f2bcb17b431",
        "hasValidationError" : false,
        "id" : "pbContainer",
        "rows" : [
          [
            {
              "type" : "component",
              "dimension" : {
                "xs" : 12,
                "sm" : 12,
                "md" : 12,
                "lg" : 12
              },
              "propertyValues" : {
                "cssClasses" : {
                  "type" : "constant",
                  "value" : ""
                },
                "hidden" : {
                  "type" : "constant",
                  "value" : false
                },
                "labelHidden" : {
                  "type" : "constant",
                  "value" : true
                },
                "label" : {
                  "type" : "interpolation",
                  "value" : "Default label"
                },
                "labelPosition" : {
                  "type" : "constant",
                  "value" : "top"
                },
                "labelWidth" : {
                  "type" : "constant",
                  "value" : 4
                },
                "allowHTML" : {
                  "type" : "constant",
                  "value" : true
                },
                "text" : {
                  "type" : "interpolation",
                  "value" : "Selectați din tabelul de mai jos imobilul dorit."
                },
                "alignment" : {
                  "type" : "constant",
                  "value" : "center"
                }
              },
              "reference" : "b010d02e-09fa-4eff-a232-83df6d1355e4",
              "hasValidationError" : false,
              "id" : "pbText"
            }
          ]
        ]
      }
    ],
    [
      {
        "type" : "container",
        "dimension" : {
          "xs" : 12,
          "sm" : 12,
          "md" : 2,
          "lg" : 6
        },
        "propertyValues" : {
          "cssClasses" : {
            "type" : "constant",
            "value" : ""
          },
          "hidden" : {
            "type" : "constant",
            "value" : false
          },
          "repeatedCollection" : {
            "type" : "variable",
            "value" : ""
          }
        },
        "reference" : "12c10fc9-0086-401c-a9ba-7e67827e1051",
        "hasValidationError" : false,
        "id" : "pbContainer",
        "rows" : [
          [ ]
        ]
      },
      {
        "type" : "container",
        "dimension" : {
          "xs" : 12,
          "sm" : 12,
          "md" : 8,
          "lg" : 6
        },
        "propertyValues" : {
          "cssClasses" : {
            "type" : "constant",
            "value" : ""
          },
          "hidden" : {
            "type" : "constant",
            "value" : false
          },
          "repeatedCollection" : {
            "type" : "variable",
            "value" : ""
          }
        },
        "reference" : "fa796fca-29b0-4870-ba60-f16ffa5214c8",
        "hasValidationError" : false,
        "id" : "pbContainer",
        "rows" : [
          [
            {
              "type" : "component",
              "dimension" : {
                "xs" : 12,
                "sm" : 12,
                "md" : 12,
                "lg" : 12
              },
              "propertyValues" : {
                "cssClasses" : {
                  "type" : "constant",
                  "value" : ""
                },
                "hidden" : {
                  "type" : "constant",
                  "value" : false
                },
                "allowHTML" : {
                  "type" : "constant",
                  "value" : true
                },
                "headers" : {
                  "type" : "constant",
                  "value" : [
                    "Id",
                    "Name",
                    "Description",
                    "Date"
                  ]
                },
                "type" : {
                  "type" : "constant",
                  "value" : "Bonita API"
                },
                "apiUrl" : {
                  "type" : "constant",
                  "value" : "../API/"
                },
                "params" : {
                  "type" : "constant"
                },
                "content" : {
                  "type" : "constant"
                },
                "columnsKey" : {
                  "type" : "constant"
                },
                "sortColumns" : {
                  "type" : "constant"
                },
                "selectedRow" : {
                  "type" : "variable",
                  "value" : ""
                },
                "pageSize" : {
                  "type" : "constant",
                  "value" : 10
                },
                "filter" : {
                  "type" : "constant"
                },
                "striped" : {
                  "type" : "constant",
                  "value" : true
                },
                "condensed" : {
                  "type" : "constant",
                  "value" : false
                },
                "bordered" : {
                  "type" : "constant",
                  "value" : false
                }
              },
              "reference" : "b62c0ea4-812d-4749-8928-89a8b26b0d10",
              "hasValidationError" : false,
              "id" : "pbDataTable"
            }
          ]
        ]
      }
    ]
  ],
  "assets" : [
    {
      "id" : "a8711e99-533a-4564-835c-3ea6e03a8340",
      "name" : "style.css",
      "type" : "css",
      "order" : 0,
      "external" : false
    },
    {
      "id" : "332ab98c-0d67-4fc3-9149-ce5afed03492",
      "name" : "localization.json",
      "type" : "json",
      "order" : 0,
      "external" : false
    }
  ],
  "inactiveAssets" : [ ],
  "variables" : { },
  "hasValidationError" : false,
  "uuid" : "a2dd8dbd-6125-4d68-aecf-18bb5a186864",
  "type" : "form",
  "description" : "Page generated with Bonita UI designer"
}